[
    {
        "id": "1234",
        "date": "Tuesday - Aug 21, 2016",
        "time": "11AM",
        "title": "Angel Tree Kit Assembly",
        "details": "Come help assemble Angel Tree Kits for asomeone in need. Last year Casrr P Collins assembled 5500kits to help people in the Community."
    },
    {
        "id": "1235",
        "date": "Tuesday - Aug 21, 2016",
        "time": "11AM",
        "title": "Angel Tree Kit Assembly",
        "details": "Come help assemble Angel Tree Kits for asomeone in need. Last year Casrr P Collins assembled 5500kits to help people in the Community."
    }
]